evotoolbox/__init__.py
evotoolbox/toolbox.py
evotoolbox/binary/BaseTransformer.py
evotoolbox/binary/QTransformer.py
evotoolbox/binary/SigmoidTransformer.py
evotoolbox/binary/ThresholdTransformer.py
evotoolbox/binary/VTransformer.py
evotoolbox/binary/__init__.py
evotoolbox/fitness/BaseFitness.py
evotoolbox/fitness/MultiobjectiveFitness.py
evotoolbox/fitness/__init__.py
evotoolbox/initializers/BaseInitializer.py
evotoolbox/initializers/GreedyInitializer.py
evotoolbox/initializers/OblInitializer.py
evotoolbox/initializers/RandomInitializer.py
evotoolbox/initializers/__init__.py
evotoolbox/optimizers/BaseOptimizer.py
evotoolbox/optimizers/__init__.py
evotoolbox/optimizers/boa.py
evotoolbox/optimizers/ga.py
evotoolbox/optimizers/gwo.py
evotoolbox/optimizers/hho.py
evotoolbox/optimizers/ssa.py
evotoolbox/optimizers/ssade.py
evotoolbox/optimizers/ssagwo.py
evotoolbox-0.0.2.dist-info/METADATA
evotoolbox-0.0.2.dist-info/WHEEL
evotoolbox-0.0.2.dist-info/top_level.txt
evotoolbox-0.0.2.dist-info/RECORD
