Metadata-Version: 2.1
Name: evotoolbox
Version: 0.0.2
Summary: A toolbox for feature selection using evolutionary algorithms
Home-page: https://github.com/shakiba-shb/evotoolbox
Author: Shakiba Shahbandegan
Author-email: sh.shahbandegan@gmail.com
License: MIT
Platform: UNKNOWN
Classifier: License :: OSI Approved :: MIT License
Classifier: Programming Language :: Python :: 3
Classifier: Programming Language :: Python :: 3.7
Requires-Dist: numpy
Requires-Dist: scikit-learn
